read_nas/__init__.py
read_nas/load_and_adjust_time.py
read_nas-0.1.dist-info/METADATA
read_nas-0.1.dist-info/WHEEL
read_nas-0.1.dist-info/top_level.txt
read_nas-0.1.dist-info/RECORD
